py_ai_studio/__init__.py
py_ai_studio/api.py
py_ai_studio-0.0.1.dist-info/METADATA
py_ai_studio-0.0.1.dist-info/WHEEL
py_ai_studio-0.0.1.dist-info/top_level.txt
py_ai_studio-0.0.1.dist-info/RECORD
