Metadata-Version: 2.1
Name: py-ai-studio
Version: 0.0.1
Summary: AI Studio API
Home-page: UNKNOWN
Author: Daniel David
Author-email: UNKNOWN
License: GPL
Platform: UNKNOWN
Requires-Dist: Pyrebase
